mcp_m365_filesearch/__init__.py
mcp_m365_filesearch/logger_config.py
mcp_m365_filesearch/msal_auth.py
mcp_m365_filesearch/msgraph_util.py
mcp_m365_filesearch/server.py
iflow_mcp_godwin3737_mcp_m365_filesearch-0.1.0.dist-info/METADATA
iflow_mcp_godwin3737_mcp_m365_filesearch-0.1.0.dist-info/WHEEL
iflow_mcp_godwin3737_mcp_m365_filesearch-0.1.0.dist-info/entry_points.txt
iflow_mcp_godwin3737_mcp_m365_filesearch-0.1.0.dist-info/top_level.txt
iflow_mcp_godwin3737_mcp_m365_filesearch-0.1.0.dist-info/RECORD
