Metadata-Version: 2.4
Name: iflow-mcp_godwin3737_mcp-m365-filesearch
Version: 0.1.0
Summary: Add your description here
Requires-Python: >=3.11
Requires-Dist: beautifulsoup4>=4.13.3
Requires-Dist: greenlet>=3.1.1
Requires-Dist: html5lib>=1.1
Requires-Dist: llama-index-core>=0.12.29
Requires-Dist: llama-index[all]>=0.12.29
Requires-Dist: mcp[cli]>=1.6.0
Requires-Dist: msal>=1.32.0
Requires-Dist: openpyxl>=3.1.5
Requires-Dist: pandas>=2.2.3
Requires-Dist: pillow>=11.1.0
Requires-Dist: pymupdf>=1.25.5
Requires-Dist: python-docx>=1.1.2
Requires-Dist: python-pptx>=1.0.2
Requires-Dist: torch>=2.6.0
Requires-Dist: transformers>=4.51.1
